<xml xmlns="http://www.w3.org/1999/xhtml"><block type="commandConstructor" id="e.TYYn%~}KNWlSBFHM8i" x="137" y="87"><field name="name">AntiKB</field><field name="argsLengths"></field><field name="keyChar">Z</field></block><block type="procedures_defnoreturn" id="*x*!Fl8zjSUrB6PASNg~" x="138" y="213"><field name="NAME">initialize the command</field><comment pinned="false" h="80" w="160">Initialized the command</comment><statement name="STACK"><block type="com.logiccity.minecraft.api.GameControl.setPlayerKnockBackEnabled" id="~QY(Wzs8H^@/-gY;-rW~"><value name="enabled"><block type="logic_boolean" id="rQZkBocS9*J~%CxF8%=B"><field name="BOOL">FALSE</field></block></value></block></statement></block><block type="procedures_defnoreturn" id="d!f0h:Z,(*[L!MFXnClz" x="138" y="363"><field name="NAME">cleanup command</field><comment pinned="false" h="80" w="160">Cleanup command</comment><statement name="STACK"><block type="com.logiccity.minecraft.api.GameControl.setPlayerKnockBackEnabled" id=";Hh;Mj=tu!/*SG@+?(B?"><value name="enabled"><block type="logic_boolean" id="8AH/mqTZN_|A0}F!Deo#"><field name="BOOL">TRUE</field></block></value></block></statement></block></xml>